{
  "kind": "singleType",
  "collectionName": "headers",
  "info": {
    "name": "Header",
    "description": ""
  },
  "options": {
    "increments": true,
    "timestamps": true,
    "draftAndPublish": true
  },
  "pluginOptions": {
    "i18n": {
      "localized": true
    }
  },
  "attributes": {
    "background_image": {
      "collection": "file",
      "via": "related",
      "allowedTypes": [
        "images",
        "files",
        "videos"
      ],
      "plugin": "upload",
      "required": false,
      "pluginOptions": {
        "i18n": {
          "localized": true
        }
      }
    },
    "logo_image": {
      "model": "file",
      "via": "related",
      "allowedTypes": [
        "images",
        "files",
        "videos"
      ],
      "plugin": "upload",
      "required": false,
      "pluginOptions": {
        "i18n": {
          "localized": true
        }
      }
    },
    "social_fb_label": {
      "pluginOptions": {
        "i18n": {
          "localized": false
        }
      },
      "type": "string"
    },
    "social_fb_link": {
      "pluginOptions": {
        "i18n": {
          "localized": false
        }
      },
      "type": "string"
    }
  }
}
